topic-3/__init__.py
topic-3/evaluate.py
topic-3/main.py
topic-3/test.py
topic-3/train.py
topic-3/datasets/TimeDataset.py
topic-3/datasets/__init__.py
topic-3/models/CNN.py
topic-3/models/GDN.py
topic-3/models/GRU.py
topic-3/models/LSTM.py
topic-3/models/LSTMVAE.py
topic-3/models/MLP.py
topic-3/models/RNN.py
topic-3/models/Transformer.py
topic-3/models/__init__.py
topic-3/scripts/__init__.py
topic-3/scripts/process_steel.py
topic-3/show_img/__init__.py
topic-3/util/__init__.py
topic-3/util/data.py
topic-3/util/env.py
topic-3/util/ewc.py
topic-3/util/ewc_utils.py
topic-3/util/iostream.py
topic-3/util/loss_func.py
topic-3/util/net_struct.py
topic-3/util/preprocess.py
topic-3/util/util_time.py
topic_3/__init__.py
topic_3/evaluate.py
topic_3/main.py
topic_3/test.py
topic_3/test_p.py
topic_3/train.py
topic_3/Description/__init__.py
topic_3/Description/System_modeling_and_node_importance/System_modeling_and_node_importance_main.py
topic_3/Description/System_modeling_and_node_importance/__init__.py
topic_3/Description/Time_Casual/__init__.py
topic_3/Description/Time_Casual/adf_test.py
topic_3/Description/Time_Casual/feature_selection.py
topic_3/Description/Time_Casual/get_causality.py
topic_3/Description/Time_Casual/get_optimal_lag_order.py
topic_3/Description/quality/__init__.py
topic_3/Description/quality/functions.py
topic_3/Description/quality/main.py
topic_3/Description/quality/utils.py
topic_3/Forecast/__init__.py
topic_3/Forecast/CNN_GRU_Attention/__init__.py
topic_3/Forecast/CNN_GRU_Attention/main.py
topic_3/Forecast/CNN_GRU_Attention/wwl_oil_data_prepare.py
topic_3/Forecast/CNN_GRU_Attention/wwl_oil_model.py
topic_3/Forecast/CNN_GRU_Attention/wwl_oil_test.py
topic_3/Forecast/CNN_GRU_Attention/wwl_oil_train.py
topic_3/Forecast/CNN_GRU_Attention/wwl_power_data_prepare.py
topic_3/Forecast/CNN_GRU_Attention/dataset/__init__.py
topic_3/Forecast/CNN_GRU_Attention/fig_saves/__init__.py
topic_3/Forecast/CNN_GRU_Attention/saves/__init__.py
topic_3-2.1.3.dist-info/LICENSE
topic_3-2.1.3.dist-info/METADATA
topic_3-2.1.3.dist-info/WHEEL
topic_3-2.1.3.dist-info/top_level.txt
topic_3-2.1.3.dist-info/RECORD
