Metadata-Version: 2.1
Name: topic_3
Version: 2.1.3
Summary: steel ewc test package
Author: PYJ
Author-email: 3463146475@qq.com
Requires-Python: >=3.6
License-File: LICENSE
